crawl/__init__.py
crawl/crawler.py
crawl/loader.py
crawl/rate_limiter.py
crawl/rate_limiting_loader.py
bfg_crawl-0.1.2.dist-info/WHEEL
bfg_crawl-0.1.2.dist-info/METADATA
bfg_crawl-0.1.2.dist-info/RECORD
