Metadata-Version: 2.3
Name: bfg-crawl
Version: 0.1.2
Summary: Add your description here
Author: Lei Zhao
Author-email: Lei Zhao <8961794+leizha@users.noreply.github.com>
Requires-Dist: scikit-learn>=1.7.2
Requires-Python: >=3.13
